latio/__init__.py
latio/core.py
latio/workers.py
latio-1.2.7.dist-info/licenses/LICENSE
latio-1.2.7.dist-info/METADATA
latio-1.2.7.dist-info/WHEEL
latio-1.2.7.dist-info/entry_points.txt
latio-1.2.7.dist-info/top_level.txt
latio-1.2.7.dist-info/RECORD
