Metadata-Version: 2.4
Name: latio
Version: 1.2.7
Summary: Latio Application Security Tester - Uses OpenAPI to scan for security issues in code changes
Home-page: https://github.com/latiotech/LAST
Author: James Berthoty
Author-email: james@latio.tech
License: GPL-3.0 license
Classifier: Development Status :: 5 - Production/Stable
Classifier: Intended Audience :: Developers
Classifier: Topic :: Software Development :: Libraries :: Python Modules
Classifier: Topic :: Security
Classifier: Programming Language :: Python :: 3
Classifier: Programming Language :: Python :: 3.8
Classifier: Programming Language :: Python :: 3.9
Classifier: Programming Language :: Python :: 3.10
Classifier: Programming Language :: Python :: 3.11
Requires-Python: >=3.8
License-File: LICENSE
Requires-Dist: openai==1.70.0
Requires-Dist: PyGithub==2.1.1
Requires-Dist: Requests==2.31.0
Requires-Dist: google-generativeai==0.3.2
Requires-Dist: pylance==0.9.17
Requires-Dist: ipython==8.21.0
Requires-Dist: openai-agents==0.0.7
Dynamic: author
Dynamic: author-email
Dynamic: classifier
Dynamic: description
Dynamic: description-content-type
Dynamic: home-page
Dynamic: license
Dynamic: license-file
Dynamic: requires-dist
Dynamic: requires-python
Dynamic: summary
